qiwi_api/__init__.py
qiwi_api/enums.py
qiwi_api/exceptions.py
qiwi_api/qiwi_api.py
qiwi_api-1.1.dist-info/METADATA
qiwi_api-1.1.dist-info/RECORD
qiwi_api-1.1.dist-info/WHEEL
qiwi_api-1.1.dist-info/top_level.txt
