Metadata-Version: 2.1
Name: qiwi-api
Version: 1.1
Summary: Qiwi api wrapper
Home-page: https://github.com/helow19274/qiwi_api
Author: Helow19274
Author-email: helow@helow19274.tk
License: UNKNOWN
Platform: UNKNOWN
Classifier: License :: OSI Approved :: MIT License
Classifier: Operating System :: OS Independent
Classifier: Programming Language :: Python :: 3
Classifier: Programming Language :: Python :: 3.5
Classifier: Programming Language :: Python :: 3.6
Classifier: Programming Language :: Python :: 3.7
Classifier: Programming Language :: Python :: Implementation :: CPython
Classifier: Programming Language :: Python :: Implementation :: PyPy
Requires-Dist: requests
